{
    "places": [
        {
            "name": "Nizuc",
            "rating": 4.5,
            "reviews": 407,
            "category": "Restaurante",
            "address": "Cra. 44 #18-6",
            "hours": [
                {
                    "open": "12:00 p.m.",
                    "close": "3:30 p.m."
                },
                {
                    "open": "7:00 p.m.",
                    "close": "11:00 p.m."
                }
            ],
            "services": [
                "Consumo en el lugar",
                "Retiros en la puerta",
                "Entrega sin contacto"
            ],
            "location": {
                "latitude": 4.137961205818293,
                "longitude": -73.64344506966309
            },
            "images": [
                "https://lh5.googleusercontent.com/p/AF1QipN_rlZ-G732deI8D0UnQIKVd1ctDR50zxb1TC99=w408-h306-k-no"
            ],
            "google_maps_url": "https://www.google.com/maps/search/?api=1&query=Nizuc+Cra.+44+%2318-6"
        },
        {
            "name": "Restaurante Tierra del Fuego",
            "rating": 4.4,
            "reviews": 219,
            "category": "Restaurante",
            "address": "Cl. 15 #40-01",
            "hours": [
                {
                    "open": "12:00 p.m.",
                    "close": "11:00 p.m."
                }
            ],
            "services": [
                "Consumo en el lugar",
                "Retiros en la puerta",
                "Entrega sin contacto"
            ],
            "location": {
                "latitude": 4.134431109214601,
                "longitude": -73.64011928467201
            },
            "images": [
                "https://lh5.googleusercontent.com/p/AF1QipMs_gfRLDm8ggBEgi6MaULPe8pm0vPHIH-XzI88=w408-h272-k-no"
            ],
            "google_maps_url": "https://www.google.com/maps/search/?api=1&query=Restaurante+Tierra+del+Fuego+Cl.+15+%2340-01"
        },
        {
            "name": "Bastimento Restaurante",
            "rating": 4.5,
            "reviews": 501,
            "category": "Restaurante",
            "address": "Cl. 15 #40-101 local 241",
            "hours": [
                {
                    "open": "12:00 p.m.",
                    "close": "10:00 p.m."
                }
            ],
            "services": [
                "Consumo en el lugar",
                "Para llevar",
                "Entrega sin contacto"
            ],
            "location": {
                "latitude": 4.134661237088642,
                "longitude": -73.64035770775274
            },
            "images": [
                "https://lh5.googleusercontent.com/p/AF1QipMbf6eMgT-EIrxJ9Md5EY5HJRRZ7-wiNDpqr6IO=w408-h544-k-no"
            ],
            "google_maps_url": "https://www.google.com/maps/search/?api=1&query=Bastimento+Restaurante+Cl.+15+%2340-101+local+241"
        },
        {
            "name": "Santa Clara restaurante bar",
            "rating": 4.5,
            "reviews": 140,
            "category": "Restaurante",
            "address": "Cl. 41b #31-32",
            "hours": [
                {
                    "open": "12:00 p.m.",
                    "close": "11:00 p.m."
                }
            ],
            "services": [
                "Consumo en el lugar",
                "Retiros en la puerta",
                "Entrega a domicilio"
            ],
            "location": {
                "latitude": 4.155182822322632,
                "longitude": -73.63953798517609
            },
            "images": [
                "https://lh5.googleusercontent.com/p/AF1QipOKW5wpS82DDuvJCuYmr6NjdZBY7XPQdt2uTz6O=w519-h240-k-no"
            ],
            "google_maps_url": "https://www.google.com/maps/search/?api=1&query=Santa+Clara+restaurante+bar+Cl.+41b+%2331-32"
        },
        {
            "name": "Restaurante Love",
            "rating": 4.8,
            "reviews": 41,
            "category": "Restaurante",
            "address": "Cl. 19 #40-14",
            "hours": [
                {
                    "open": "12:00 p.m.",
                    "close": "3:00 p.m."
                },
                {
                    "open": "6:00 p.m.",
                    "close": "11:00 p.m."
                }
            ],
            "services": [
                "Consumo en el lugar",
                "Para llevar",
                "Entrega a domicilio"
            ],
            "location": {
                "latitude": 4.136270399390394,
                "longitude": -73.63872422884295
            },
            "images": [
                "https://lh5.googleusercontent.com/p/AF1QipMxZgKK_LjqjeDOhuiiroQLpB_EPZphpFyEL8Qm=w408-h544-k-no"
            ],
            "google_maps_url": "https://www.google.com/maps/search/?api=1&query=Restaurante+Love+Cl.+19+%2340-14"
        },
        {
            "name": "Oliva Mediterránea",
            "rating": 4.5,
            "reviews": 745,
            "category": "Restaurante",
            "address": "El Trapiche Plaza Gourmet Barrio El Buque, Cl. 15 #44b-90",
            "hours": [
                {
                    "open": "12:00 p.m.",
                    "close": "11:00 p.m."
                }
            ],
            "services": [
                "Consumo en el lugar",
                "Retiros en la puerta",
                "Entrega sin contacto"
            ],
            "location": {
                "latitude": 4.1371693422278835,
                "longitude": -73.64471107094069
            },
            "images": [
                "https://lh5.googleusercontent.com/p/AF1QipNgqgX7_-Jq9H_fLmDufwmi0P3aMGMzxAdtX68I=w425-h240-k-no"
            ],
            "google_maps_url": "https://www.google.com/maps/search/?api=1&query=Oliva+Mediterránea+El+Trapiche+Plaza+Gourmet+Barrio+El+Buque+Cl.+15+%2344b-90"
        },
        {
            "name": "GHL Hotel Grand Villavicencio",
            "rating": 4.6,
            "reviews": 4374,
            "category": "Hotel",
            "address": "Villavicencio, Colombia",
            "hours": [
                {
                    "open": "24:00",
                    "close": "24:00"
                }
            ],
            "services": [
                "Piscina",
                "Spa",
                "Estacionamiento gratuito",
                "Desayuno incluido"
            ],
            "location": {
                "latitude": 4.13488971276208,
                "longitude": -73.63755388650988
            },
            "images": [
                "https://lh5.googleusercontent.com/p/AF1QipMAiYVTQTDRaFsLgUb8VSWKsjoxeyPf596ibSw=w408-h272-k-no"
            ],
            "google_maps_url": "https://www.google.com/maps/search/?api=1&query=GHL+Hotel+Grand+Villavicencio"
        },
        {
            "name": "Hotel Boutique Armoni",
            "rating": 4.3,
            "reviews": 236,
            "category": "Hotel",
            "address": "Villavicencio, Colombia",
            "hours": [
                {
                    "open": "24:00",
                    "close": "24:00"
                }
            ],
            "services": [
                "Estacionamiento gratuito",
                "Desayuno incluido",
                "Wi-Fi gratis",
                "Aire acondicionado"
            ],
            "location": {
                "latitude": 4.1348691109397055,
                "longitude": -73.63862747116083
            },
            "images": [
                "https://lh5.googleusercontent.com/p/AF1QipOGTubvIwgEy2Qtuc4Va5xwbzdbVV3J8zubaWmP=w408-h272-k-no"
            ],
            "google_maps_url": "https://www.google.com/maps/search/?api=1&query=Hotel+Boutique+Armoni"
        }
    ]
}